inkscape_qrcode/__init__.py
inkscape_qrcode/qrcode.py
inkscape_qrcode/_segno/__init__.py
inkscape_qrcode/_segno/consts.py
inkscape_qrcode/_segno/encoder.py
inkscape_qrcode/_segno/utils.py
inkscape_qrcode-0.1.4.dist-info/DESCRIPTION.rst
inkscape_qrcode-0.1.4.dist-info/METADATA
inkscape_qrcode-0.1.4.dist-info/RECORD
inkscape_qrcode-0.1.4.dist-info/WHEEL
inkscape_qrcode-0.1.4.dist-info/metadata.json
inkscape_qrcode-0.1.4.dist-info/top_level.txt
