Metadata-Version: 2.0
Name: inkscape-qrcode
Version: 0.1.4
Summary: QR Code and Micro QR Code generator for Inkscape
Home-page: https://github.com/heuer/inkscape-qrcode/
Author: Lars Heuer
Author-email: heuer@semagia.com
License: GPL2
Keywords: QR Code,Micro QR Code,ISO/IEC 18004,ISO/IEC 18004:2006(E),ISO/IEC 18004:2015(E),qrcode,QR,barcode,matrix,2D,Inkscape
Platform: any
Classifier: Development Status :: 4 - Beta
Classifier: Intended Audience :: Developers
Classifier: License :: OSI Approved :: BSD License
Classifier: License :: OSI Approved :: GNU General Public License v2 (GPLv2)
Classifier: Operating System :: OS Independent
Classifier: Programming Language :: Python
Classifier: Programming Language :: Python :: 2
Classifier: Programming Language :: Python :: 2.6
Classifier: Programming Language :: Python :: 2.7
Classifier: Topic :: Multimedia :: Graphics
Classifier: Topic :: Printing
Classifier: Topic :: Software Development :: Libraries :: Python Modules
Classifier: Topic :: Utilities
